MANIFEST.in
README.rst
setup.py
cassinyspawner/__init__.py
cassinyspawner/swarmspawner.py
requirements/base.txt
requirements/tests.txt
uva_swarmspawner.egg-info/PKG-INFO
uva_swarmspawner.egg-info/SOURCES.txt
uva_swarmspawner.egg-info/dependency_links.txt
uva_swarmspawner.egg-info/requires.txt
uva_swarmspawner.egg-info/top_level.txt